[
  {
    "name": "Troubleshooter",
    "filename": "IconPerks_troubleshooter.png",
    "imageUrl": "https://drive.google.com/uc?export=view&id=10MmNqYb9-tpMO1wxVsKhiyED3OLPF6lP"
  },
  {
    "name": "Dramaturgy",
    "filename": "iconPerks_Dramaturgy.png",
    "imageUrl": "https://drive.google.com/uc?export=view&id=13iFiavvCv_FnA1QM2cuVk-6sqLS-b9l2"
  },
  {
    "name": "Mettle of Man",
    "filename": "iconPerks_MettleOfMan.png",
    "imageUrl": "https://drive.google.com/uc?export=view&id=15RNvp19eMlPK_2dIueCnTTxet5fvYvtb"
  },
  {
    "name": "Repressed Alliance",
    "filename": "iconPerks_RepressedAlliance.png",
    "imageUrl": "https://drive.google.com/uc?export=view&id=15VWLd4ZNY02do-qjwYl2z2pwRyy4_8kl"
  },
  {
    "name": "Deception",
    "filename": "iconPerks_Deception.png",
    "imageUrl": "https://drive.google.com/uc?export=view&id=17dYhkDuwU9T3-ph6LwqpLiQr3PAyFVl9"
  },
  {
    "name": "Red Herring",
    "filename": "iconPerks_RedHerring.png",
    "imageUrl": "https://drive.google.com/uc?export=view&id=17g_Pf5qIsVuxjIp38025Euxp5U65gOZR"
  },
  {
    "name": "Resurgence",
    "filename": "iconPerks_Resurgence.png",
    "imageUrl": "https://drive.google.com/uc?export=view&id=18Ao8etQmYkevdPAT8RU7fU5ArsZdywWd"
  },
  {
    "name": "Shoulder the Burden",
    "filename": "T_UI_iconsPerks_ShoulderTheBurden.png",
    "imageUrl": "https://drive.google.com/uc?export=view&id=18UZfZla64lovJkfslLT6UZx__3xgb3qK"
  },
  {
    "name": "No Mither",
    "filename": "iconPerks_NoMither.png",
    "imageUrl": "https://drive.google.com/uc?export=view&id=18oo5kWA5A3rcObcwAA94d5GEPW7UV0Os"
  },
  {
    "name": "Urban Evasion",
    "filename": "iconPerks_UrbanEvasion.png",
    "imageUrl": "https://drive.google.com/uc?export=view&id=19G045HG3SjowNpnoYJ5vB15OqTgrGy2a"
  },
  {
    "name": "Flashbang",
    "filename": "iconPerks_Flashbang.png",
    "imageUrl": "https://drive.google.com/uc?export=view&id=19UHxYvGgrHNWW2lF5K8uWdMgs_-wj8LL"
  },
  {
    "name": "Scene Partner",
    "filename": "iconPerks_ScenePartner.png",
    "imageUrl": "https://drive.google.com/uc?export=view&id=19u-Ye_BOojkRherDKcrIQVRYjbqnEfu9"
  },
  {
    "name": "Cut Loose",
    "filename": "iconPerks_CutLoose.png",
    "imageUrl": "https://drive.google.com/uc?export=view&id=1AXFxlPqzMC6MZgsgN64FrTx7PVWMq7W3"
  },
  {
    "name": "Empathic Connection",
    "filename": "iconPerks_EmpathicConnection.png",
    "imageUrl": "https://drive.google.com/uc?export=view&id=1ArUR7DSsjaW2WONmsoC3FA3Pn6Q90tJW"
  },
  {
    "name": "Dark Sense",
    "filename": "iconPerks_DarkSense.png",
    "imageUrl": "https://drive.google.com/uc?export=view&id=1BqLDYhmRlyMvX-sHdo38L7U9QnNkFI7A"
  },
  {
    "name": "Strength in Shadows",
    "filename": "iconsPerks_StrengthInShadows.png",
    "imageUrl": "https://drive.google.com/uc?export=view&id=1C-2SWjd5WAWuDes_DkfohyohrEkxWmVG"
  },
  {
    "name": "Clairvoyance",
    "filename": "iconPerks_Clairvoyance.png",
    "imageUrl": "https://drive.google.com/uc?export=view&id=1C5_qeNHxfutj2TvFa9nsZpYWAi3cnv4I"
  },
  {
    "name": "Scavenger",
    "filename": "IconPerks_scavenger.png",
    "imageUrl": "https://drive.google.com/uc?export=view&id=1CRarM975b3AenEwZK3EE53s5GcdOJLfy"
  },
  {
    "name": "Buckle Up",
    "filename": "iconPerks_BuckleUp.png",
    "imageUrl": "https://drive.google.com/uc?export=view&id=1Ea_PDeBMxlQx-RdK9w9GVYTPPpisIIgX"
  },
  {
    "name": "Distortion",
    "filename": "iconPerks_Distortion.png",
    "imageUrl": "https://drive.google.com/uc?export=view&id=1FizsWJv5eoc8wRyGrp5ClPXnuS4XX65T"
  },
  {
    "name": "Dance with Me",
    "filename": "iconPerks_DanceWithMe.png",
    "imageUrl": "https://drive.google.com/uc?export=view&id=1GU-XoUcfBJD35WkYi2Ycc1uC1Y0F7hhD"
  },
  {
    "name": "Still Sight",
    "filename": "iconPerks_StillSight.png",
    "imageUrl": "https://drive.google.com/uc?export=view&id=1GowjvhDKp7RIfcNIpshfNH4t0LyNUEXj"
  },
  {
    "name": "Lucky Break",
    "filename": "iconPerks_LuckyBreak.png",
    "imageUrl": "https://drive.google.com/uc?export=view&id=1GxaLASKD4AegdrE-3WLZ0ryNlkdHycwx"
  },
  {
    "name": "Exultation",
    "filename": "iconPerks_Exultation.png",
    "imageUrl": "https://drive.google.com/uc?export=view&id=1H94IEQv583wcD3g3w9wdnrDK3Jt9T91K"
  },
  {
    "name": "Invocation: Treacherous Crows",
    "filename": "T_UI_iconsPerks_InvocationTreacherousCrows.png",
    "imageUrl": "https://drive.google.com/uc?export=view&id=1H_uchyhy7cBCnPQY6dEUhqYFxaESVY7g"
  },
  {
    "name": "Clean Break",
    "filename": "T_UI_iconsPerks_CleanBreak.png",
    "imageUrl": "https://drive.google.com/uc?export=view&id=1JBoO9Dvf0q6McaC8GMwiKFqGQTppLAgT"
  },
  {
    "name": "Camaraderie",
    "filename": "iconPerks_Camaraderie.png",
    "imageUrl": "https://drive.google.com/uc?export=view&id=1JHeEb9RHzstc3fQHmsKC2prN9DkbItGs"
  },
  {
    "name": "Mirrored Illusion",
    "filename": "iconPerks_MirroredIllusion.png",
    "imageUrl": "https://drive.google.com/uc?export=view&id=1JNvnWWUhRQH1rTST0kN8GoFQdPV4TP-2"
  },
  {
    "name": "Friendly Competition",
    "filename": "iconPerks_FriendlyCompetition.png",
    "imageUrl": "https://drive.google.com/uc?export=view&id=1JUt9scSnQOdc-sjxC8YHPqXaDKetQ0HN"
  },
  {
    "name": "Power Struggle",
    "filename": "iconPerks_PowerStruggle.png",
    "imageUrl": "https://drive.google.com/uc?export=view&id=1KEsOFwgR4vwW_2cKlEVk1H1frQm6n1dP"
  },
  {
    "name": "Calm Spirit",
    "filename": "iconPerks_CalmSpirit.png",
    "imageUrl": "https://drive.google.com/uc?export=view&id=1KH0f5HTz_ZymmQPoE1PSMhXOkXxEuQEb"
  },
  {
    "name": "Self-Preservation",
    "filename": "iconPerks_Self-Preservation.png",
    "imageUrl": "https://drive.google.com/uc?export=view&id=1KjIn_-7lbYrKX_ubhMBmrr0nGucP1OOW"
  },
  {
    "name": "Overcome",
    "filename": "T_iconPerks_Overcome.png",
    "imageUrl": "https://drive.google.com/uc?export=view&id=1KsIPv7YMw3kcpy6zPVCGpv4NWyzxg1n9"
  },
  {
    "name": "Built to Last",
    "filename": "iconPerks_BuiltToLast.png",
    "imageUrl": "https://drive.google.com/uc?export=view&id=1MyN57onJFZzzL4kboOYqcM2xYbRx1FMi"
  },
  {
    "name": "Wake Up!",
    "filename": "iconPerks_WakeUp.png",
    "imageUrl": "https://drive.google.com/uc?export=view&id=1NDVpWu9lyacGwnz1ZUJZ8DijY5_dzW4o"
  },
  {
    "name": "Light Footed",
    "filename": "iconPerks_LightFooted.png",
    "imageUrl": "https://drive.google.com/uc?export=view&id=1NItwIoqfltd8jaZSBb4FbJwV_m6oCAq5"
  },
  {
    "name": "Dead Hard",
    "filename": "iconPerks_DeadHard.png",
    "imageUrl": "https://drive.google.com/uc?export=view&id=1NwUEheLd_s1pFXTkmabbo1OgXd42RlPg"
  },
  {
    "name": "Leader",
    "filename": "iconPerks_Leader.png",
    "imageUrl": "https://drive.google.com/uc?export=view&id=1PH4H4IEnNTzIITYhgNxdBFnV-AECbA2t"
  },
  {
    "name": "Visionary",
    "filename": "iconPerks_Visionary.png",
    "imageUrl": "https://drive.google.com/uc?export=view&id=1PWvkIxcnjDeUb146KVnGpewhGcJ_lX_2"
  },
  {
    "name": "Potential Energy",
    "filename": "iconPerks_PotentialEnergy.png",
    "imageUrl": "https://drive.google.com/uc?export=view&id=1Q61BNK1VAdXJmYlMfgNF40eyYWdXTZ09"
  },
  {
    "name": "Inner Strength",
    "filename": "iconPerks_innerStrength.png",
    "imageUrl": "https://drive.google.com/uc?export=view&id=1QlLSwjUhT6-20pAP-Dawk1B-ixcZWPXT"
  },
  {
    "name": "Specialist",
    "filename": "iconPerks_Specialist.png",
    "imageUrl": "https://drive.google.com/uc?export=view&id=1R3N3FLITsmdpCC4PtHv9RwrygrsVJT7V"
  },
  {
    "name": "Unbreakable",
    "filename": "iconPerks_Unbreakable.png",
    "imageUrl": "https://drive.google.com/uc?export=view&id=1ReqX-fadW54q4Z-C6JfCwruea6JVH2PT"
  },
  {
    "name": "Detectives Hunch",
    "filename": "iconPerks_DetectivesHunch.png",
    "imageUrl": "https://drive.google.com/uc?export=view&id=1RhN6FFbBj9Z8btXsEZPKom1v_DSXblhT"
  },
  {
    "name": "Fogwise",
    "filename": "iconPerks_Fogwise.png",
    "imageUrl": "https://drive.google.com/uc?export=view&id=1RnNPhnPoicHCKfTfu2E6z__L3WzHxpzT"
  },
  {
    "name": "Sole Survivor",
    "filename": "iconPerks_SoleSurvivor.png",
    "imageUrl": "https://drive.google.com/uc?export=view&id=1RoKwloe6Mu3Dbu54rIfAuWCWW4ZeOy3B"
  },
  {
    "name": "Tenacity",
    "filename": "iconPerks_Tenacity.png",
    "imageUrl": "https://drive.google.com/uc?export=view&id=1Rvcedo_4xrcMBn_820K6EkFEv9J0vy9q"
  },
  {
    "name": "Spine Chill",
    "filename": "iconPerks_SpineChill.png",
    "imageUrl": "https://drive.google.com/uc?export=view&id=1SCcFBlmhGAVL4zf3M3n9JHgXD7eVcWx_"
  },
  {
    "name": "Stake Out",
    "filename": "iconPerks_StakeOut.png",
    "imageUrl": "https://drive.google.com/uc?export=view&id=1TC1ugcFvvHmCHr7nzRAz_X6uzF5VH984"
  },
  {
    "name": "We'll Make It",
    "filename": "iconPerks_WellMakeIt.png",
    "imageUrl": "https://drive.google.com/uc?export=view&id=1TwWNDUc_WtSkIOGYrUsxMzZbJyWE1w11"
  },
  {
    "name": "Smash Hit",
    "filename": "iconPerks_SmashHit.png",
    "imageUrl": "https://drive.google.com/uc?export=view&id=1Vbw5Va-z7YXU7FV0PfGZvwaASCTnRgem"
  },
  {
    "name": "Moment of Glory",
    "filename": "iconPerks_MomentOfGlory.png",
    "imageUrl": "https://drive.google.com/uc?export=view&id=1W8S-lypZvNIkloJn9Idm0wh_ajZkUgsV"
  },
  {
    "name": "No One Left Behind",
    "filename": "iconPerks_NoOneLeftBehind.png",
    "imageUrl": "https://drive.google.com/uc?export=view&id=1W9UBDlDKkL_I_UC68ND8Uev2rCT_-vvI"
  },
  {
    "name": "Technician",
    "filename": "iconPerks_Technician.png",
    "imageUrl": "https://drive.google.com/uc?export=view&id=1W9k2ISmNMZ70dV3ICA7XgKi3sPXF_V9s"
  },
  {
    "name": "Object of Obsession",
    "filename": "iconPerks_ObjectOfObsession.png",
    "imageUrl": "https://drive.google.com/uc?export=view&id=1WMkrtagEEREDCQTrmYlyRo-VRgUDnwMr"
  },
  {
    "name": "Left Behind",
    "filename": "iconPerks_LeftBehind.png",
    "imageUrl": "https://drive.google.com/uc?export=view&id=1X2kDC7FqlLkmpvQciiSu2b0jp-Dd87B_"
  },
  {
    "name": "Champion of Light",
    "filename": "iconsPerks_ChampionOfLight.png",
    "imageUrl": "https://drive.google.com/uc?export=view&id=1YPdFNHiCHRgRpp_AXh603lZvUrN6QpiJ"
  },
  {
    "name": "For the People",
    "filename": "iconPerks_ForThePeople.png",
    "imageUrl": "https://drive.google.com/uc?export=view&id=1YS4Wrn2wKd0FDNBPUI_Gvt8kFff7xwmo"
  },
  {
    "name": "Empathy",
    "filename": "iconPerks_Empathy.png",
    "imageUrl": "https://drive.google.com/uc?export=view&id=1Z2qwshzUH5mURe73josSjGWCgwT2cp42"
  },
  {
    "name": "Parental Guidance",
    "filename": "iconPerks_ParentalGuidance.png",
    "imageUrl": "https://drive.google.com/uc?export=view&id=1Z7W39D1sJ4nyWgbr1sD6ahsSWChh6QrK"
  },
  {
    "name": "Open Handed",
    "filename": "iconPerks_OpenHanded.png",
    "imageUrl": "https://drive.google.com/uc?export=view&id=1ZW2tu0o8vyLEZ4wVntaYJwVulUnjNNCn"
  },
  {
    "name": "Poised",
    "filename": "iconPerks_Poised.png",
    "imageUrl": "https://drive.google.com/uc?export=view&id=1ZtnxU-nhSest_wgyOaBsSHjZK3-Ye4Kw"
  },
  {
    "name": "Saboteur",
    "filename": "iconPerks_Saboteur.png",
    "imageUrl": "https://drive.google.com/uc?export=view&id=1Zu86QeMC4qzzS0AYMHjf3rDi4E5DZ3O3"
  },
  {
    "name": "Self Care",
    "filename": "iconPerks_SelfCare.png",
    "imageUrl": "https://drive.google.com/uc?export=view&id=1_o8829-UE9F8iwFnnmAmooIPpq6SccB6"
  },
  {
    "name": "Diversion",
    "filename": "iconPerks_Diversion.png",
    "imageUrl": "https://drive.google.com/uc?export=view&id=1_uuLkStwwM_nBkyXWE0RbXH8jYcaudTL"
  },
  {
    "name": "Iron Will",
    "filename": "iconPerks_IronWill.png",
    "imageUrl": "https://drive.google.com/uc?export=view&id=1aGeJVD5GPd-lOFl6F6B103a0uNTIhZZU"
  },
  {
    "name": "Pharmacy",
    "filename": "iconPerks_Pharmacy.png",
    "imageUrl": "https://drive.google.com/uc?export=view&id=1aSxqEqG7hzDcIHQb5IFFhr49LmShZwIJ"
  },
  {
    "name": "Teamwork: Power of Two",
    "filename": "iconPerks_TeamworkPowerOfTwo.png",
    "imageUrl": "https://drive.google.com/uc?export=view&id=1ecHJjZrn6HqVMeZvVtkKGyB3ceqy2G9B"
  },
  {
    "name": "Vigil",
    "filename": "iconPerks_Vigil.png",
    "imageUrl": "https://drive.google.com/uc?export=view&id=1f0GvhntlrvUw1jNNz8o6vU1VN4yy9qZx"
  },
  {
    "name": "Wicked",
    "filename": "iconsPerks_Wicked.png",
    "imageUrl": "https://drive.google.com/uc?export=view&id=1fM5_W8k7VqAl7QaGBQbOgyZmzUxytvoU"
  },
  {
    "name": "Chemical Trap",
    "filename": "iconPerks_ChemicalTrap.png",
    "imageUrl": "https://drive.google.com/uc?export=view&id=1g0mHDcxX0jnHh1j-HHEB0x5jIdoHWRkf"
  },
  {
    "name": "Plunderers Instinct",
    "filename": "iconPerks_PlunderersInstinct.png",
    "imageUrl": "https://drive.google.com/uc?export=view&id=1h_B5HzyzqWR0H4WNH-w6bc2QD-T4SIml"
  },
  {
    "name": "Fast Track",
    "filename": "iconPerks_FastTrack.png",
    "imageUrl": "https://drive.google.com/uc?export=view&id=1i7CIOQ3g8orsbrtHR05nUAQqkMmN63k4"
  },
  {
    "name": "Desperate Measures",
    "filename": "iconPerks_DesperateMeasures.png",
    "imageUrl": "https://drive.google.com/uc?export=view&id=1iEeourSHuNxCIZSNcSZM023OVX4Z6f08"
  },
  {
    "name": "Lucky Star",
    "filename": "iconPerks_LuckyStar.png",
    "imageUrl": "https://drive.google.com/uc?export=view&id=1iGiZoSoD7rRalDx5MWvM2XkCBa3b7IyG"
  },
  {
    "name": "Decisive Strike",
    "filename": "iconPerks_DecisiveStrike.png",
    "imageUrl": "https://drive.google.com/uc?export=view&id=1iye5GbR6oGI__BTkr8YQczIuWvKC-sFr"
  },
  {
    "name": "Hope",
    "filename": "iconPerks_Hope.png",
    "imageUrl": "https://drive.google.com/uc?export=view&id=1j7zjftzwJAsogZYdi9BTYxad8W-bnjWC"
  },
  {
    "name": "Quick and Quiet",
    "filename": "iconPerks_QuickAndQuiet.png",
    "imageUrl": "https://drive.google.com/uc?export=view&id=1jxi3iXlg7kx8Qc1RuHyZ9ipCFccMVeBM"
  },
  {
    "name": "ProveThyself",
    "filename": "iconPerks_ProveThyself.png",
    "imageUrl": "https://drive.google.com/uc?export=view&id=1lNRY5VhTQQZuveXHJG-NBCJ743On-XB-"
  },
  {
    "name": "Second Wind",
    "filename": "iconPerks_secondWind.png",
    "imageUrl": "https://drive.google.com/uc?export=view&id=1lRpc2iVriaAlKLRcfzTQ2fLMv4xpy9rL"
  },
  {
    "name": "This is Not Happening",
    "filename": "iconPerks_ThisIsNotHappening.png",
    "imageUrl": "https://drive.google.com/uc?export=view&id=1mKRdhohqOUB7kPGJ_CXDtNBT5caMZWdh"
  },
  {
    "name": "Rookie Spirit",
    "filename": "iconPerks_RookieSpirit.png",
    "imageUrl": "https://drive.google.com/uc?export=view&id=1nNxNP6LWSvB7my3u4Q6d88C8gIeLxxTc"
  },
  {
    "name": "Eyes of Belmont",
    "filename": "iconPerks_EyesOfBelmont.png",
    "imageUrl": "https://drive.google.com/uc?export=view&id=1ndx65nXIRGyQk8IMqaO7L58jcgnhovFw"
  },
  {
    "name": "Deliverance",
    "filename": "iconPerks_Deliverance.png",
    "imageUrl": "https://drive.google.com/uc?export=view&id=1p_0IX7teT_XsQnUzRORQKxysBWxlcsqw"
  },
  {
    "name": "Counterforce",
    "filename": "iconPerks_Counterforce.png",
    "imageUrl": "https://drive.google.com/uc?export=view&id=1pd59Itys8AD-k1TxGmZ5pukV0GdSuYkI"
  },
  {
    "name": "Head On",
    "filename": "iconPerks_HeadOn.png",
    "imageUrl": "https://drive.google.com/uc?export=view&id=1pk1mFuJvAD2HSo-JZN8pCCQ0TSdNIlCf"
  },
  {
    "name": "Lithe",
    "filename": "iconPerks_Lithe.png",
    "imageUrl": "https://drive.google.com/uc?export=view&id=1q9C9GQr1HGTSoY5PqFpudZlvv9rGYnCf"
  },
  {
    "name": "Premonition",
    "filename": "iconPerks_Premonition.png",
    "imageUrl": "https://drive.google.com/uc?export=view&id=1qBkqPGR1xG8bj1TaG3Y7yJkgu7yfrRHf"
  },
  {
    "name": "Made for This",
    "filename": "IconPerks_madeForThis.png",
    "imageUrl": "https://drive.google.com/uc?export=view&id=1qMIGY-YAPQ4jYe_Xf02MMpNs74QL7bxv"
  },
  {
    "name": "Small Game",
    "filename": "iconPerks_SmallGame.png",
    "imageUrl": "https://drive.google.com/uc?export=view&id=1r_sw216ic6ijkYCTJBU_z9ypc29C_0YR"
  },
  {
    "name": "Deja Vu",
    "filename": "iconPerks_DejaVu.png",
    "imageUrl": "https://drive.google.com/uc?export=view&id=1t_IkKa99mGhRCk3ee2bRUYOfTjNGwOeg"
  },
  {
    "name": "Wiretap",
    "filename": "iconPerks_Wiretap.png",
    "imageUrl": "https://drive.google.com/uc?export=view&id=1vTJ0inAF3i9OD1mN1WFV4b_Vr9T-GrOB"
  },
  {
    "name": "Plot Twist",
    "filename": "iconPerks_PlotTwist.png",
    "imageUrl": "https://drive.google.com/uc?export=view&id=1vW_O3-0BL5PMRgPxmxPRQfcJK9oniADn"
  },
  {
    "name": "We're Gonna Live Forever",
    "filename": "iconPerks_WereGonnaLiveForever.png",
    "imageUrl": "https://drive.google.com/uc?export=view&id=1vwomZId7fWWtekOxLKH3UP89HeIM4sfh"
  },
  {
    "name": "Up the Ante",
    "filename": "iconPerks_UpTheAnte.png",
    "imageUrl": "https://drive.google.com/uc?export=view&id=1wEXe-t5Jee9t4G6HUs7kLZwyscJ7S5I9"
  },
  {
    "name": "Quick Gambit",
    "filename": "iconPerks_VittoriosGambit.png",
    "imageUrl": "https://drive.google.com/uc?export=view&id=1wGJZ07Dp2P7JzhnpoTmlYWPOY2yjOmTg"
  },
  {
    "name": "Sprint Burst",
    "filename": "iconPerks_SprintBurst.png",
    "imageUrl": "https://drive.google.com/uc?export=view&id=1wmLjYkjQbY1KxRpVbyTw9NgSLKKa4SyL"
  },
  {
    "name": "Soul Guard",
    "filename": "iconPerks_SoulGuard.png",
    "imageUrl": "https://drive.google.com/uc?export=view&id=1z9M-mV3tP2IXgJXX0zoK2i7zKSDwbKEp"
  },
  {
    "name": "Flip Flop",
    "filename": "iconPerks_FlipFlop.png",
    "imageUrl": "https://drive.google.com/uc?export=view&id=1zB1Mg8IrSiFBkT0PFfiaOc3esm_mq1OI"
  },
  {
    "name": "Kindred",
    "filename": "iconPerks_Kindred.png",
    "imageUrl": "https://drive.google.com/uc?export=view&id=1zjS-sxrwPeErzp6FyBrrBlD74OjxP6nZ"
  },
  {
    "name": "Overzealous",
    "filename": "iconPerks_Overzealous.png",
    "imageUrl": "https://drive.google.com/uc?export=view&id=10_SBen91296-TajMESPK_sRVAAgEEhQ9"
  },
  {
    "name": "Residual Manifest",
    "filename": "iconPerks_ResidualManifest.png",
    "imageUrl": "https://drive.google.com/uc?export=view&id=11AUfVsaxZjX13RRlXFdulf1yiMoGcudr"
  },
  {
    "name": "Fixated",
    "filename": "iconPerks_Fixated.png",
    "imageUrl": "https://drive.google.com/uc?export=view&id=11VOGxKMKO6ZZJgGy5robwbhFC1K8BmtT"
  },
  {
    "name": "Deadline",
    "filename": "iconsPerks_Deadline.png",
    "imageUrl": "https://drive.google.com/uc?export=view&id=11ppbKB-mW8VhK3wMCx9gHlvsAVOV6pIg"
  },
  {
    "name": "Resilience",
    "filename": "iconPerks_Resilience.png",
    "imageUrl": "https://drive.google.com/uc?export=view&id=137v03bskAtVcN62mnnOz3xWhzh5DFmAU"
  },
  {
    "name": "Reassurance",
    "filename": "iconPerks_Reassurance.png",
    "imageUrl": "https://drive.google.com/uc?export=view&id=138pJ65V6GQkSCbwLoC_GwuD_dkaDD02z"
  },
  {
    "name": "Invocation: Weaving Spiders",
    "filename": "iconsPerks_InvocationWeavingSpiders.png",
    "imageUrl": "https://drive.google.com/uc?export=view&id=19JRhODs6oOCbox9_1KSMZoiAmfveWkbW"
  },
  {
    "name": "Hyperfocus",
    "filename": "iconPerks_Hyperfocus.png",
    "imageUrl": "https://drive.google.com/uc?export=view&id=1DEhDJoTHYSHlz622Uvq_fDy3pOzkAMnb"
  },
  {
    "name": "Teamwork: Collective Stealth",
    "filename": "iconPerks_TeamworkCollectiveStealth.png",
    "imageUrl": "https://drive.google.com/uc?export=view&id=1Dh24G-6BNKEVNChVRPWl-0YJCWqUseV0"
  },
  {
    "name": "Finesse",
    "filename": "iconPerks_Finesse.png",
    "imageUrl": "https://drive.google.com/uc?export=view&id=1O--jlpKM7kACYhU8nxA7-KayXXQ4lV_K"
  },
  {
    "name": "Off the Record",
    "filename": "iconPerks_OffTheRecord.png",
    "imageUrl": "https://drive.google.com/uc?export=view&id=1O9BZCTLnQDXjn3csV6S4lvCJqW6EwLi1"
  },
  {
    "name": "Low Profile",
    "filename": "iconPerks_LowProfile.png",
    "imageUrl": "https://drive.google.com/uc?export=view&id=1RHbISBCg00R6-1i_mLMSWtfPndr_M5OG"
  },
  {
    "name": "Corrective Action",
    "filename": "T_iconPerks_CorrectiveAction.png",
    "imageUrl": "https://drive.google.com/uc?export=view&id=1ZYAmgtumL88NsXhDWCHQKbG21UuLsTFT"
  },
  {
    "name": "Solidarity",
    "filename": "iconPerks_Solidarity.png",
    "imageUrl": "https://drive.google.com/uc?export=view&id=1cJKz16t_11nQhnkElhvR80M8gGmkv1yj"
  },
  {
    "name": "Streetwise",
    "filename": "iconPerks_Streetwise.png",
    "imageUrl": "https://drive.google.com/uc?export=view&id=1e0C1pgPfiDMlen6-1hFmnnR8idTdrjVo"
  },
  {
    "name": "Inner Focus",
    "filename": "iconPerks_InnerFocus.png",
    "imageUrl": "https://drive.google.com/uc?export=view&id=1gLjEeAEO7d1Il2dDei6LBw5EzmW7KgAP"
  },
  {
    "name": "Hardened",
    "filename": "iconPerks_Hardened.png",
    "imageUrl": "https://drive.google.com/uc?export=view&id=1mJVt2ERMqzFkjFjOAbjoX7k6o1nES3lh"
  },
  {
    "name": "Reactive Healing",
    "filename": "iconPerks_ReactiveHealing.png",
    "imageUrl": "https://drive.google.com/uc?export=view&id=1pWre7LM7mCk2WUxGi9js_MrHnxKbGEwK"
  },
  {
    "name": "Slippery Meat",
    "filename": "iconPerks_SlipperyMeat.png",
    "imageUrl": "https://drive.google.com/uc?export=view&id=1roTDTP57BTJWhdC_ODMXxxVmNprlxvXq"
  },
  {
    "name": "Windows of Opportunity",
    "filename": "iconPerks_WindowsOfOpportunity.png",
    "imageUrl": "https://drive.google.com/uc?export=view&id=1smLDr8peS_5HQA5jHqv2PERxIdB3yTH9"
  },
  {
    "name": "Lightweight",
    "filename": "iconPerks_Lightweight.png",
    "imageUrl": "https://drive.google.com/uc?export=view&id=1tpZ_R9VLtOHx36v0wYPQ8F0MGO8xwIPb"
  },
  {
    "name": "Adrenaline",
    "filename": "iconPerks_Adrenaline.png",
    "imageUrl": "https://drive.google.com/uc?export=view&id=10IGIB1tdGri7ItTggPBkmy2MwXhYry-p"
  },
  {
    "name": "Background Player",
    "filename": "iconPerks_BackgroundPlayer.png",
    "imageUrl": "https://drive.google.com/uc?export=view&id=12PJgjxcGb9kXzmnXjBhGQ914oYNEku7Y"
  },
  {
    "name": "Blood Pact",
    "filename": "iconPerks_BloodPact.png",
    "imageUrl": "https://drive.google.com/uc?export=view&id=14EunbB0zRFWGMHgfHs2EIP0BZVtGrF5F"
  },
  {
    "name": "Blood Rush",
    "filename": "iconPerks_BloodRush.png",
    "imageUrl": "https://drive.google.com/uc?export=view&id=14pxwEWnFUCfImh3mSBEH6U0icSiHCpY6"
  },
  {
    "name": "Autodidact",
    "filename": "iconPerks_Autodidact.png",
    "imageUrl": "https://drive.google.com/uc?export=view&id=1FmXqqgXnD3VSY-guBcJhukamqaP5SwaV"
  },
  {
    "name": "Better Than New",
    "filename": "iconPerks_BetterThanNew.png",
    "imageUrl": "https://drive.google.com/uc?export=view&id=1G4I-WI3c5uhrzQvND2dDy1G3ZJYBzfOs"
  },
  {
    "name": "Boil Over",
    "filename": "iconPerks_BoilOver.png",
    "imageUrl": "https://drive.google.com/uc?export=view&id=1Ml_QDfecHFcgXWrntydkUfJDh2htIA39"
  },
  {
    "name": "Aftercare",
    "filename": "iconPerks_Aftercare.png",
    "imageUrl": "https://drive.google.com/uc?export=view&id=1Nr6dfZAeQ-8OjG7RxdKStsZzqqggXhCz"
  },
  {
    "name": "Better Together",
    "filename": "iconPerks_betterTogether.png",
    "imageUrl": "https://drive.google.com/uc?export=view&id=1O3HkYK9LxTvjjWunjYXCHl0aIf9uQQur"
  },
  {
    "name": "Boon: Shadow Step",
    "filename": "iconPerks_BoonShadowStep.png",
    "imageUrl": "https://drive.google.com/uc?export=view&id=1OZgjAy3dnQaxpFei0zZ4qOJy6DiMBxy-"
  },
  {
    "name": "Alert",
    "filename": "iconPerks_Alert.png",
    "imageUrl": "https://drive.google.com/uc?export=view&id=1PDPlcZJ1Bruey8Xq9OPlcDUAaMfUQI5m"
  },
  {
    "name": "Appraisal",
    "filename": "iconPerks_Appraisal.png",
    "imageUrl": "https://drive.google.com/uc?export=view&id=1QNIIvNi-CskOBIKdIRBx_0vLxxt4--NY"
  },
  {
    "name": "Breakdown",
    "filename": "iconPerks_Breakdown.png",
    "imageUrl": "https://drive.google.com/uc?export=view&id=1Vj35_3IUtGWhgkv9EgfE4JMl6SJCTX0n"
  },
  {
    "name": "Bite the Bullet",
    "filename": "iconPerks_BiteTheBullet.png",
    "imageUrl": "https://drive.google.com/uc?export=view&id=1ZuevNFV3ZgCYfVE7-k7eNZjsQWqhbETh"
  },
  {
    "name": "Boon: Circle of Healing",
    "filename": "iconPerks_BoonCircleOfHealing.png",
    "imageUrl": "https://drive.google.com/uc?export=view&id=1aYcWNOHkEeZ3LbUnFFuYbeCBiRJSVCz5"
  },
  {
    "name": "Boon: Illumination",
    "filename": "iconsPerks_Illumination.png",
    "imageUrl": "https://drive.google.com/uc?export=view&id=1c0nR4APXmUyYdmK9PPBdCEo_DnJAB-C4"
  },
  {
    "name": "Borrowed Time",
    "filename": "iconPerks_BorrowedTime.png",
    "imageUrl": "https://drive.google.com/uc?export=view&id=1cOAOJiqJa9vHXBuMnuLD4qRrvL_-hSj_"
  },
  {
    "name": "Boon: Dark Theory",
    "filename": "iconPerks_DarkTheory.png",
    "imageUrl": "https://drive.google.com/uc?export=view&id=1fIFDg3Y-QtCQkZJuo0wrATn7zmVvR3Rt"
  },
  {
    "name": "Bardic Inspiration",
    "filename": "iconPerks_BardicInspiration.png",
    "imageUrl": "https://drive.google.com/uc?export=view&id=1fkHxGiyz58QQWJcR7YGHDwohCoOcNhKO"
  },
  {
    "name": "Spies from the Shadows",
    "filename": "iconPerks_SpiesFromTheShadows.png",
    "imageUrl": "https://drive.google.com/uc?export=view&id=1gWzmp-BNhEi8JKR-MAPxBrpRHMh1z9aE"
  },
  {
    "name": "Any Means Necessary",
    "filename": "iconPerks_AnyMeansNecessary.png",
    "imageUrl": "https://drive.google.com/uc?export=view&id=1h_uR3AaLMIkE3h1A3-WXviXveqj1S3vf"
  },
  {
    "name": "Botany Knowledge",
    "filename": "iconPerks_BotanyKnowledge.png",
    "imageUrl": "https://drive.google.com/uc?export=view&id=1jNv3gaxh6hSslcOBVqW3ETowKSktoYlG"
  },
  {
    "name": "Breakout",
    "filename": "iconPerks_Breakout.png",
    "imageUrl": "https://drive.google.com/uc?export=view&id=1jqkjKvbFMMrHe1-KGBdy3EQ8R93Ugkm8"
  },
  {
    "name": "Balanced Landing",
    "filename": "iconPerks_BalancedLanding.png",
    "imageUrl": "https://drive.google.com/uc?export=view&id=1jzGKTMAakSOLIG4jruto57ml3GIIXvaM"
  },
  {
    "name": "Babysitter",
    "filename": "iconPerks_babySitter.png",
    "imageUrl": "https://drive.google.com/uc?export=view&id=1m4nZxuNxdFo0jx94mLxZwbf8lKCSM6iq"
  },
  {
    "name": "Bond",
    "filename": "iconPerks_Bond.png",
    "imageUrl": "https://drive.google.com/uc?export=view&id=1p435SQ4KMG9XW3OsQVY3c6FosswmGemO"
  },
  {
    "name": "Blast Mine",
    "filename": "iconPerks_BlastMine.png",
    "imageUrl": "https://drive.google.com/uc?export=view&id=1ssqDEmklM0SW6tM2i5Ui-y98ip-okvsS"
  },
  {
    "name": "Ace in the Hole",
    "filename": "iconPerks_AceInTheHole.png",
    "imageUrl": "https://drive.google.com/uc?export=view&id=1u24d-XajnNe4kWRWyX1zIMaBF3wnjlrA"
  }
]